pch2csd/__init__.py
pch2csd/app.py
pch2csd/csdgen.py
pch2csd/parse.py
pch2csd/patch.py
pch2csd/udo.py
pch2csd/util.py
pch2csd/resources/__init__.py
pch2csd/resources/mod_type_name.json
pch2csd/resources/value_maps.json
pch2csd/resources/templates/csd_footer.txt
pch2csd/resources/templates/csd_ft_rectifier.txt
pch2csd/resources/templates/csd_ft_waveforms.txt
pch2csd/resources/templates/csd_header.txt
pch2csd/resources/templates/modules/1.txt
pch2csd/resources/templates/modules/100.txt
pch2csd/resources/templates/modules/1000.txt
pch2csd/resources/templates/modules/103.txt
pch2csd/resources/templates/modules/105.txt
pch2csd/resources/templates/modules/106.txt
pch2csd/resources/templates/modules/112.txt
pch2csd/resources/templates/modules/113.txt
pch2csd/resources/templates/modules/114.txt
pch2csd/resources/templates/modules/116.txt
pch2csd/resources/templates/modules/117.txt
pch2csd/resources/templates/modules/121.txt
pch2csd/resources/templates/modules/123.txt
pch2csd/resources/templates/modules/124.txt
pch2csd/resources/templates/modules/127.txt
pch2csd/resources/templates/modules/128.txt
pch2csd/resources/templates/modules/130.txt
pch2csd/resources/templates/modules/131.txt
pch2csd/resources/templates/modules/132.txt
pch2csd/resources/templates/modules/134.txt
pch2csd/resources/templates/modules/139.txt
pch2csd/resources/templates/modules/140.txt
pch2csd/resources/templates/modules/141.txt
pch2csd/resources/templates/modules/142.txt
pch2csd/resources/templates/modules/143.txt
pch2csd/resources/templates/modules/144.txt
pch2csd/resources/templates/modules/146.txt
pch2csd/resources/templates/modules/147.txt
pch2csd/resources/templates/modules/148.txt
pch2csd/resources/templates/modules/149.txt
pch2csd/resources/templates/modules/15.txt
pch2csd/resources/templates/modules/156.txt
pch2csd/resources/templates/modules/157.txt
pch2csd/resources/templates/modules/159.txt
pch2csd/resources/templates/modules/161.txt
pch2csd/resources/templates/modules/164.txt
pch2csd-0.1.dev320.dist-info/LICENSE.md
pch2csd-0.1.dev320.dist-info/METADATA
pch2csd-0.1.dev320.dist-info/WHEEL
pch2csd-0.1.dev320.dist-info/entry_points.txt
pch2csd-0.1.dev320.dist-info/top_level.txt
pch2csd-0.1.dev320.dist-info/RECORD
