Metadata-Version: 2.1
Name: pch2csd
Version: 0.1.dev320
Summary: Convert Clavia Nord Modular G2 patches to the Csound code.
Home-page: https://github.com/gleb812/pch2csd
Author: Gleb Rogozinsky, Mikhail Chesnokov, Eugene Cherny
License: MIT
Keywords: csound code-generation
Platform: any
Classifier: Development Status :: 2 - Pre-Alpha
Classifier: Topic :: Utilities
Classifier: License :: OSI Approved :: BSD License
Classifier: Environment :: Console
Classifier: Programming Language :: Python :: 3
Classifier: Operating System :: OS Independent
Requires-Dist: bitarray
Requires-Dist: tabulate
